Metadata-Version: 2.1
Name: libhttprequests
Version: 0.2
Summary: Code samples regarding the module Pytools from DevPro Platform
Home-page: https://github.com/mauriciodoerr/pytools/tree/main/libhttprequests
Author: Mauricio Doerr
Author-email: mauricio.doerr@gmail.com
License:                     GNU GENERAL PUBLIC LICENSE
Classifier: Development Status :: 2 - Pre-Alpha
Classifier: Environment :: Console
Classifier: Intended Audience :: Developers
Classifier: License :: OSI Approved :: GNU Affero General Public License v3 or later (AGPLv3+)
Classifier: Operating System :: OS Independent
Classifier: Programming Language :: Python
Classifier: Framework :: Pytest
License-File: LICENSE
